durakonline/__init__.py
durakonline/authorization.py
durakonline/durakonline.py
durakonline/friend.py
durakonline/game.py
durakonline/socket_listener.py
durakonline/utils/__init__.py
durakonline/utils/objects.py
durakonline.py-3.3.0.dist-info/LICENSE
durakonline.py-3.3.0.dist-info/METADATA
durakonline.py-3.3.0.dist-info/WHEEL
durakonline.py-3.3.0.dist-info/top_level.txt
durakonline.py-3.3.0.dist-info/RECORD
