Metadata-Version: 2.1
Name: durakonline.py
Version: 3.3.0
Summary: A library to create Durak Online bots.
Home-page: https://github.com/Zakovskiy/durakonline.py
Author: Zakovskiy
Author-email: gogrugu@gmail.com
License: MIT
Download-URL: https://github.com/Zakovskiy/durakonline.py/tarball/master
Keywords: durak,online,durakonline,durakonline.py,durakonline-bot,rstgame,rstgames,api,socket,python,python3,python3.x,zakovskiy,official
Platform: UNKNOWN
Requires-Dist: aiohttp
Requires-Dist: loguru
Requires-Dist: requests
Requires-Dist: setuptools
